LICENSE
MANIFEST.in
README.rst
setup.py
bin/idstools-dumpdynamicrules
bin/idstools-eve2pcap
bin/idstools-gensidmsgmap
bin/idstools-rulecat
bin/idstools-rulemod
bin/idstools-u2eve
bin/idstools-u2fast
bin/idstools-u2json
bin/idstools-u2spewfoo
idstools/__init__.py
idstools/maps.py
idstools/net.py
idstools/packet.py
idstools/rule.py
idstools/snort.py
idstools/suricata.py
idstools/unified2.py
idstools/util.py
idstools.egg-info/PKG-INFO
idstools.egg-info/SOURCES.txt
idstools.egg-info/dependency_links.txt
idstools.egg-info/top_level.txt
idstools/compat/__init__.py
idstools/compat/ordereddict.py
idstools/compat/argparse/__init__.py
idstools/compat/argparse/argparse.py
idstools/rulecat/__init__.py
idstools/rulecat/extract.py
idstools/rulecat/loghandler.py
idstools/rulecat/configs/__init__.py
idstools/rulecat/configs/disable.conf
idstools/rulecat/configs/drop.conf
idstools/rulecat/configs/enable.conf
idstools/rulecat/configs/modify.conf
idstools/rulecat/configs/threshold.in
idstools/scripts/__init__.py
idstools/scripts/dumpdynamicrules.py
idstools/scripts/eve2pcap.py
idstools/scripts/gensidmsgmap.py
idstools/scripts/rulecat.py
idstools/scripts/rulemod.py
idstools/scripts/u2eve.py
idstools/scripts/u2fast.py
idstools/scripts/u2json.py
idstools/scripts/u2spewfoo.py
tests/test_classificationmap.py
tests/test_net.py
tests/test_packet.py
tests/test_rule.py
tests/test_rulecat.py
tests/test_signaturemap.py
tests/test_snort.py
tests/test_suricata.py
tests/test_unified2.py
tests/test_util.py