Metadata-Version: 2.1
Name: idstools
Version: 0.6.5
Summary: IDS Utility Library
Home-page: https://github.com/jasonish/py-idstools
Author: Jason Ish
Author-email: ish@unx.ca
License: BSD
Classifier: License :: OSI Approved :: BSD License
License-File: LICENSE
